onfido/__init__.py
onfido/admin.py
onfido/api.py
onfido/apps.py
onfido/data/supported_applicant_countries.json
onfido/data.py
onfido/decorators.py
onfido/helpers.py
onfido/management/__init__.py
onfido/management/commands/__init__.py
onfido/management/commands/onfido_sync.py
onfido/migrations/0001_initial.py
onfido/migrations/0002_event.py
onfido/migrations/0003_auto_20161023_1455.py
onfido/migrations/0004_auto_20161023_1648.py
onfido/migrations/0005_remove_event_user.py
onfido/migrations/0006_rename_event_fields.py
onfido/migrations/0007_rename_onfido_id_verbose_name.py
onfido/migrations/0008_rename_event_created_at.py
onfido/migrations/0009_add_is_clear_field.py
onfido/migrations/0010_convert_raw_fields_to_jsonb.py
onfido/migrations/0011_add_indexes_to_status_fields.py
onfido/migrations/0012_add_event_received_at_timestamp.py
onfido/migrations/0013_update_report_type_choices.py
onfido/migrations/0014_update_status_result_choices.py
onfido/migrations/0015_update_check_type_field.py
onfido/migrations/0016_update_applicant_user_field.py
onfido/migrations/0017_auto_20210304_0241.py
onfido/migrations/0018_remove_isclear_from_basestatus_model.py
onfido/migrations/0019_add_new_status_choices.py
onfido/migrations/__init__.py
onfido/models/__init__.py
onfido/models/applicant.py
onfido/models/base.py
onfido/models/check.py
onfido/models/event.py
onfido/models/report.py
onfido/settings.py
onfido/signals.py
onfido/urls.py
onfido/views.py
django_onfido-2.2.dist-info/LICENSE
django_onfido-2.2.dist-info/WHEEL
django_onfido-2.2.dist-info/METADATA
django_onfido-2.2.dist-info/RECORD
