Metadata-Version: 2.1
Name: django-onfido
Version: 2.2
Summary: Django app for integration with Onfido.
Home-page: https://github.com/yunojuno/django-onfido
License: MIT
Author: YunoJuno
Author-email: code@yunojuno.com
Maintainer: YunoJuno
Maintainer-email: code@yunojuno.com
Requires-Python: >=3.7,<4.0
Classifier: Development Status :: 4 - Beta
Classifier: Environment :: Web Environment
Classifier: Framework :: Django
Classifier: Framework :: Django :: 3.1
Classifier: Framework :: Django :: 3.2
Classifier: Framework :: Django :: 4.0
Classifier: License :: OSI Approved :: MIT License
Classifier: Operating System :: OS Independent
Classifier: Programming Language :: Python :: 3
Classifier: Programming Language :: Python :: 3 :: Only
Classifier: Programming Language :: Python :: 3.10
Classifier: Programming Language :: Python :: 3.7
Classifier: Programming Language :: Python :: 3.8
Classifier: Programming Language :: Python :: 3.9
Requires-Dist: django
Requires-Dist: python-dateutil
Requires-Dist: requests
Requires-Dist: simplejson
Project-URL: Documentation, https://github.com/yunojuno/django-onfido
Project-URL: Repository, https://github.com/yunojuno/django-onfido
